hysteresis/__init__.py
hysteresis/baseFuncs.py
hysteresis/climate.py
hysteresis/compare.py
hysteresis/curve.py
hysteresis/data.py
hysteresis/defaultDataFuncs.py
hysteresis/defaultPlotFuncs.py
hysteresis/env.py
hysteresis/envelope.py
hysteresis/protocol.py
hysteresis/resample.py
hysteresis/plotSpecial/__init__.py
hysteresis/plotSpecial/animate.py
hysteresis/plotSpecial/core.py
hysteresis/plotSpecial/guiPlot.py
hysteresis-2.0.5.dist-info/LICENSE
hysteresis-2.0.5.dist-info/METADATA
hysteresis-2.0.5.dist-info/WHEEL
hysteresis-2.0.5.dist-info/top_level.txt
hysteresis-2.0.5.dist-info/RECORD
