Metadata-Version: 2.1
Name: hysteresis
Version: 2.0.5
Summary: Hysteresis data processing tools.
Author-email: Christian Slotboom <christian.slotboom@gmail.com>
License: Apache License
Project-URL: Homepage, https://github.com/cslotboom/Hysteresis
Project-URL: Documentation, https://hysteresis.readthedocs.io/en/latest/
Keywords: hysteresis,data processing,diagrams
Classifier: Development Status :: 5 - Production/Stable
Classifier: Intended Audience :: Science/Research
Classifier: Intended Audience :: Developers
Classifier: Programming Language :: Python
Classifier: Programming Language :: Python :: 3
Classifier: Programming Language :: Python :: 3.9
Classifier: Programming Language :: Python :: 3.10
Classifier: Programming Language :: Python :: 3.11
Classifier: Programming Language :: Python :: 3.12
Classifier: Programming Language :: Python :: 3 :: Only
Classifier: Topic :: Software Development
Classifier: Topic :: Scientific/Engineering
Classifier: Operating System :: Microsoft :: Windows
Classifier: Operating System :: POSIX
Classifier: Operating System :: Unix
Classifier: Operating System :: MacOS
Requires-Python: >=3.9
License-File: LICENSE
Requires-Dist: numpy
Requires-Dist: matplotlib
Requires-Dist: scipy
